[
  {
    "line": 1,
    "elements": [
      {
        "line": 3,
        "name": "Common step for all steps",
        "description": "",
        "type": "background",
        "keyword": "Background",
        "steps": [
          {
            "result": {
              "duration": 5984000000,
              "status": "passed"
            },
            "line": 4,
            "name": "user launches application",
            "match": {
              "location": "step_def.HomePageSteps.user_launches_application()"
            },
            "keyword": "Given "
          }
        ]
      },
      {
        "start_timestamp": "2021-03-07T01:49:43.609Z",
        "line": 50,
        "name": "Existing user should be able to sign in",
        "description": "",
        "id": "home-page-functionalities;existing-user-should-be-able-to-sign-in",
        "type": "scenario",
        "keyword": "Scenario",
        "steps": [
          {
            "result": {
              "duration": 1948000000,
              "status": "passed"
            },
            "line": 51,
            "name": "user clicks sign in button",
            "match": {
              "location": "step_def.HomePageSteps.user_clicks_sign_in_button()"
            },
            "keyword": "When "
          },
          {
            "result": {
              "duration": 375000000,
              "status": "passed"
            },
            "line": 52,
            "name": "user enters valid email and password",
            "match": {
              "location": "step_def.HomePageSteps.user_enters_valid_email_and_password()"
            },
            "keyword": "And "
          },
          {
            "result": {
              "duration": 1728000000,
              "status": "passed"
            },
            "line": 53,
            "name": "user clicks submit button",
            "match": {
              "location": "step_def.HomePageSteps.user_clicks_submit_button()"
            },
            "keyword": "And "
          },
          {
            "result": {
              "duration": 44000000,
              "status": "passed"
            },
            "line": 54,
            "name": "user is on the AccountPage",
            "match": {
              "location": "step_def.HomePageSteps.user_is_on_the_account_page()"
            },
            "keyword": "Then "
          }
        ],
        "tags": [
          {
            "name": "@signin"
          }
        ]
      }
    ],
    "name": "Home Page Functionalities",
    "description": "",
    "id": "home-page-functionalities",
    "keyword": "Feature",
    "uri": "file:src/test/resources/Features/HomePage.feature",
    "tags": []
  }
]